package_name/__init__.py
package_name/file1_name.py
package_name/file2_name.py
simplestructure-0.0.1.dist-info/METADATA
simplestructure-0.0.1.dist-info/WHEEL
simplestructure-0.0.1.dist-info/top_level.txt
simplestructure-0.0.1.dist-info/RECORD
