Metadata-Version: 2.2
Name: simplestructure
Version: 0.0.1
Summary: Create a package using the simple structure of a module.
Home-page: https://github.com/karinfaraujo/simplestructure
Author: karinf
Author-email: karinf.araujo@gmail.com
Requires-Python: >=3.8
Dynamic: author
Dynamic: author-email
Dynamic: description
Dynamic: description-content-type
Dynamic: home-page
Dynamic: requires-python
Dynamic: summary
